{
  "type": "FeatureCollection",
  "features": [
    {
      "type": "Feature",
      "id": "9fd8ed73-ff76-43cd-933b-b7642a774d9b.fid-2106f6ad_18acb9ac4c0_-13b8",
      "geometry": {
        "type": "MultiLineString",
        "coordinates": [
          [
            [
              28.96612143888947,
              47.06755637042481
            ],
        
            
              [
                  28.973693847656254,
                  47.06684799015448
              ],
              [
                  28.970603942871097,
                  47.05234716672978
              ],
              [
                  28.97575378417969,
                  47.0500079548944
              ],
              [
                  28.97232055664063,
                  47.03737443807156
              ],
              [
                  28.97472381591797,
                  47.034800577106964
              ],
              [
                  28.96682739257813,
                  47.02824837080608
              ],
              [
                  28.97953033447266,
                  47.01443930276005
              ],
              [
                  28.968200683593754,
                  47.01045975590944
              ],

                [
                    28.981933593750004,
                    47.00086080525214
                ],
                [
                    28.998413085937504,
                    46.986107836605754
                ],
                [
                    29.005622863769535,
                    46.96736803860756
                ],
                [
                    29.007339477539066,
                    46.95448061777255
                ],
                [
                    29.011802673339844,
                    46.94182449351122
                ],
                [
                    29.00596618652344,
                    46.92588289494367
                ]
          ]
        ]
      },
      "geometry_name": "geom",
      "properties": {
        "roadindex": "chisinau ring road 2",
        "roadcategory": "M"
      }
    }
  ],
  "totalFeatures": "unknown",
  "numberReturned": 1,
  "timeStamp": "2023-09-25T09:17:45.671Z",
  "crs": {
    "type": "name",
    "properties": {
      "name": "urn:ogc:def:crs:EPSG::3857"
    }
  }
}